raise_assert/__init__.py
raise_assert/raise_assert.py
raise_assert-0.1.dist-info/METADATA
raise_assert-0.1.dist-info/WHEEL
raise_assert-0.1.dist-info/top_level.txt
raise_assert-0.1.dist-info/RECORD
