Metadata-Version: 2.1
Name: raise-assert
Version: 0.1
Summary: an alternative to assert - guaranteed to raise
Home-page: https://github.com/jerabaul29/raise_assert
Author: Jean Rabault
Author-email: jean.rblt@gmail.com
License: UNKNOWN
Platform: UNKNOWN
Classifier: Programming Language :: Python :: 3
Classifier: License :: OSI Approved :: MIT License
Classifier: Operating System :: OS Independent
Requires-Python: >=3.5
